webapppacker/__init__.py
webapppacker/android_manifest.py
webapppacker/packer.py
webapppacker/utils.py
webapppacker-0.1.0.dist-info/METADATA
webapppacker-0.1.0.dist-info/WHEEL
webapppacker-0.1.0.dist-info/top_level.txt
webapppacker-0.1.0.dist-info/RECORD
