Metadata-Version: 2.1
Name: webapppacker
Version: 0.1.0
Summary: Uma biblioteca Python para empacotar aplicativos web em APKs Android
Home-page: https://github.com/seuusuario/webapppacker
Author: bruno eduardo
Author-email: hosttimer@gmail.com
Classifier: Programming Language :: Python :: 3
Classifier: License :: OSI Approved :: MIT License
Classifier: Operating System :: OS Independent
